pyveb/__init__.py
pyveb/api_client.py
pyveb/common.py
pyveb/config.py
pyveb/custom_decorators.py
pyveb/dbt_client.py
pyveb/excel_client.py
pyveb/ftp_client.py
pyveb/logger.py
pyveb/lynx_client.py
pyveb/parser.py
pyveb/request_client.py
pyveb/rs_client.py
pyveb/s3_client.py
pyveb/selenium_client.py
pyveb/sharepoint_client.py
pyveb/sharepoint_client_test.py
pyveb/spark_client.py
pyveb/sql_terra_client.py
pyveb/tableau_client.py
pyveb/tf_client.py
pyveb-0.3.63.dist-info/LICENSE
pyveb-0.3.63.dist-info/METADATA
pyveb-0.3.63.dist-info/WHEEL
pyveb-0.3.63.dist-info/RECORD
